MANIFEST.in
README.md
requirements.txt
setup.py
Pok.egg-info/PKG-INFO
Pok.egg-info/SOURCES.txt
Pok.egg-info/dependency_links.txt
Pok.egg-info/entry_points.txt
Pok.egg-info/requires.txt
Pok.egg-info/top_level.txt
p/__init__.py
p/auth.py
p/const.py
p/poc.py