Metadata-Version: 1.1
Name: Pok
Version: 0.1.0
Summary: Manage your pocket from terminal.
Home-page: https://github.com/arindampradhan/poc
Author: Arindam Pradhan
Author-email: arindampradhan10@gmail.com
License: MIT License
Download-URL: https://github.com/arindampradhan/pok/archive/v0.1.0.tar.gz
Keywords: pocket,cli,terminal
Platform: UNKNOWN
